{
    "gameData": {
        "day": "20230414",
        "expiration": "1681509540",
        "centerLetter": "A",
        "outerLetters": [
            "I",
            "K",
            "M",
            "Ü",
            "Y",
            "R"
        ],
        "words_info": {
            "word_count": 19,
            "sum_score": 92,
            "panagram_count": 1,
            "word_length": {
                "4": 6,
                "5": 8,
                "6": 2,
                "10": 1,
                "7": 1,
                "9": 1
            }
        },
        "words": [
            {
                "word": "ARAM",
                "explanation": "is. [fars.] sakitlik",
                "isPanagram": false,
                "score": 1,
                "length": 4,
                "id": 1
            },
            {
                "word": "AYAR",
                "explanation": "is. dan. 1. barama",
                "isPanagram": false,
                "score": 1,
                "length": 4,
                "id": 2
            },
            {
                "word": "MAMA",
                "explanation": "is. doğuş zamanı kömək göstərməkləməşğul olan (keçmişdə təhsilsiz",
                "isPanagram": false,
                "score": 1,
                "length": 4,
                "id": 3
            },
            {
                "word": "MAYA",
                "explanation": "is. [fars.] 1. bəzi qidalarda qıcqırma əmələ gətirən maddə. xəmir ***sı. pendir ***sı.□ *** vurmaq – bax ***lamaq 1-ci mənada",
                "isPanagram": false,
                "score": 1,
                "length": 4,
                "id": 4
            },
            {
                "word": "YARA",
                "explanation": "is. 1. bədən",
                "isPanagram": false,
                "score": 1,
                "length": 4,
                "id": 5
            },
            {
                "word": "YARI",
                "explanation": "is. tən bölünmüş iki hissədən biri. eyni ***sı. almanın ***sı. kitabın ***sını oxudum. ömrünün ***sını səhayətdə keçirmişdir",
                "isPanagram": false,
                "score": 1,
                "length": 4,
                "id": 6
            },
            {
                "word": "AYAMA",
                "explanation": "is. bir adama el tərəfindən verilənləqəb",
                "isPanagram": false,
                "score": 5,
                "length": 5,
                "id": 7
            },
            {
                "word": "AYRIM",
                "explanation": "is. azərbaycanın gədəbəy",
                "isPanagram": false,
                "score": 5,
                "length": 5,
                "id": 8
            },
            {
                "word": "MAMIR",
                "explanation": "is. bot. ali sporlu bitkilərdən ibtidaiquruluşa malik bitki. həyətin hündürhasarları rütubətdən ***la örtülmüşdü",
                "isPanagram": false,
                "score": 5,
                "length": 5,
                "id": 9
            },
            {
                "word": "MAYAK",
                "explanation": "is. [rus.] gəmilərə yol göstərməküçün siqnal işığı olan hündür qüllə. kəsildisəs",
                "isPanagram": false,
                "score": 5,
                "length": 5,
                "id": 10
            },
            {
                "word": "MAYYA",
                "explanation": "is. [sanskr.] qədim və orta əsrhind fəlsəfəsində universal anlayışlardan biri",
                "isPanagram": false,
                "score": 5,
                "length": 5,
                "id": 11
            },
            {
                "word": "YARMA",
                "explanation": "sif. 1. yarıq. qolu *** köynək. *** cibli şalvar. 2. b ax ***ça 1-ci mənada. *** odun",
                "isPanagram": false,
                "score": 5,
                "length": 5,
                "id": 12
            },
            {
                "word": "YAYIM",
                "explanation": "is. yaymaq işi",
                "isPanagram": false,
                "score": 5,
                "length": 5,
                "id": 13
            },
            {
                "word": "YAYMA",
                "explanation": "1. “***q”dan f.is. 2. is. acıtmasız xəmirdən bişirilən nazik çörək. [telli] sobanı qalayıb sac asdı",
                "isPanagram": false,
                "score": 5,
                "length": 5,
                "id": 14
            },
            {
                "word": "MAKAKA",
                "explanation": "is. [port.] əntərlər yarımfəsiləsindənolan meymun",
                "isPanagram": false,
                "score": 6,
                "length": 6,
                "id": 15
            },
            {
                "word": "YAMYAM",
                "explanation": "is. insan əti yeyən vəhşi.// vəhşi",
                "isPanagram": false,
                "score": 6,
                "length": 6,
                "id": 16
            },
            {
                "word": "YARIMAY",
                "explanation": "is. təqvim ayının yarısı. birinci***ın maaşı. ikinci ***ın planı",
                "isPanagram": false,
                "score": 7,
                "length": 7,
                "id": 17
            },
            {
                "word": "YARAMYARAM",
                "explanation": "is. zar. xanəndələrin",
                "isPanagram": false,
                "score": 10,
                "length": 10,
                "id": 18
            },
            {
                "word": "YARIMKÜRK",
                "explanation": "is. uzun olmayan kürk",
                "isPanagram": true,
                "score": 17,
                "length": 9,
                "id": 19
            }
        ]
    }
}