{
    "gameData": {
        "day": "20211022",
        "expiration": "1634939940",
        "centerLetter": "İ",
        "outterLetters": [
            "E",
            "K",
            "T",
            "L",
            "O",
            "V"
        ],
        "words_info": {
            "word_count": 21,
            "sum_score": 111,
            "panagram_count": 1,
            "word_length": {
                "8": 2,
                "11": 1,
                "4": 7,
                "5": 5,
                "6": 2,
                "7": 2,
                "9": 2
            }
        },
        "words": [
            {
                "word": "ELİT",
                "explanation": "[fr.] k.t. 1. bitki və heyvanların ən seçmə",
                "isPanagram": false,
                "score": 1,
                "length": 4
            },
            {
                "word": "ELLİ",
                "explanation": "sif. 1 vətəni",
                "isPanagram": false,
                "score": 1,
                "length": 4
            },
            {
                "word": "ELTİ",
                "explanation": "is. qardaş arvadlarının bir-birinəolan qohumluq münasibəti",
                "isPanagram": false,
                "score": 1,
                "length": 4
            },
            {
                "word": "EVLİ",
                "explanation": "sif. arvadı olan",
                "isPanagram": false,
                "score": 1,
                "length": 4
            },
            {
                "word": "KİLO",
                "explanation": "[fr.] ölçü sistemində min kiçik vahidi ifadə edən mürəkkəb adların birinci hissəsi; məs.: ***qram",
                "isPanagram": false,
                "score": 1,
                "length": 4
            },
            {
                "word": "KİVİ",
                "explanation": "is. qabığı tüklü",
                "isPanagram": false,
                "score": 1,
                "length": 4
            },
            {
                "word": "KVİT",
                "explanation": "[fr.] baş-başa",
                "isPanagram": false,
                "score": 1,
                "length": 4
            },
            {
                "word": "ELLİK",
                "explanation": "1. sif. bir yerin bütün camaatına",
                "isPanagram": false,
                "score": 5,
                "length": 5
            },
            {
                "word": "EVLİK",
                "explanation": "1. sif. evə aid",
                "isPanagram": false,
                "score": 5,
                "length": 5
            },
            {
                "word": "LİLLİ",
                "explanation": "sif. lehməli",
                "isPanagram": false,
                "score": 5,
                "length": 5
            },
            {
                "word": "TELLİ",
                "explanation": "sif. telləri olan; tellərini alnına tökmüş;saçlı",
                "isPanagram": false,
                "score": 5,
                "length": 5
            },
            {
                "word": "TİLOV",
                "explanation": "is. balıq tutmaq üçün ucu iti çəngəl; qarmaq. [imamverdi nurəddinə:] sənə *** qayıracağam",
                "isPanagram": false,
                "score": 5,
                "length": 5
            },
            {
                "word": "ETİKET",
                "explanation": "[fr.] malın",
                "isPanagram": false,
                "score": 6,
                "length": 6
            },
            {
                "word": "TİKİLİ",
                "explanation": "is. bina",
                "isPanagram": false,
                "score": 6,
                "length": 6
            },
            {
                "word": "EVLİLİK",
                "explanation": "is. evli adamın vəziyyəti",
                "isPanagram": false,
                "score": 7,
                "length": 7
            },
            {
                "word": "KOLİTLİ",
                "explanation": "sif. koliti olan",
                "isPanagram": false,
                "score": 7,
                "length": 7
            },
            {
                "word": "EKLEKTİK",
                "explanation": "is. [yun.] kit. eklektizmə meyiledən",
                "isPanagram": false,
                "score": 8,
                "length": 8
            },
            {
                "word": "LİLLİLİK",
                "explanation": "is. lilli olma; lehməlilik",
                "isPanagram": false,
                "score": 8,
                "length": 8
            },
            {
                "word": "KOTLETLİK",
                "explanation": "sif. kotlet üçün yarayan",
                "isPanagram": false,
                "score": 9,
                "length": 9
            },
            {
                "word": "EKLEKTİKLİK",
                "explanation": "is. eklektik mahiyyətdəolma. nəticələrin eklektikliyi",
                "isPanagram": false,
                "score": 11,
                "length": 11
            },
            {
                "word": "KOLLEKTİV",
                "explanation": "[lat.] ümumi məqsəd",
                "isPanagram": true,
                "score": 17,
                "length": 9
            }
        ]
    }
}